ascii_art_converter/__init__.py
ascii_art_converter/analyzer.py
ascii_art_converter/batch.py
ascii_art_converter/braille.py
ascii_art_converter/character_sets.py
ascii_art_converter/cli.py
ascii_art_converter/complexity.py
ascii_art_converter/config.py
ascii_art_converter/constants.py
ascii_art_converter/edge_detection.py
ascii_art_converter/formatters.py
ascii_art_converter/generator.py
ascii_art_converter/gif.py
ascii_art_converter/interactive.py
ascii_art_converter/presets.py
ascii_art_converter/utils.py
ascii_art_converter-1.2.0.dist-info/licenses/LICENSE.md
tests/__init__.py
tests/test_analyze_fix.py
tests/test_basic.py
tests/test_char_ratio.py
tests/test_color.py
ascii_art_converter-1.2.0.dist-info/METADATA
ascii_art_converter-1.2.0.dist-info/WHEEL
ascii_art_converter-1.2.0.dist-info/entry_points.txt
ascii_art_converter-1.2.0.dist-info/top_level.txt
ascii_art_converter-1.2.0.dist-info/RECORD
