Metadata-Version: 2.4
Name: ascii-art-converter
Version: 1.2.0
Summary: A powerful and flexible Python library for converting images to ASCII art, Braille art, and edge detection art
Home-page: https://github.com/our0boros/ascii-art-converter
Author: our0boros
Author-email: our0boros@163.com
License: MIT
Project-URL: Bug Reports, https://github.com/our0boros/ascii-art-converter/issues
Project-URL: Source, https://github.com/our0boros/ascii-art-converter/
Keywords: ascii art converter braille edge detection image processing
Classifier: Development Status :: 4 - Beta
Classifier: Intended Audience :: Developers
Classifier: Intended Audience :: End Users/Desktop
Classifier: Topic :: Artistic Software
Classifier: Topic :: Multimedia :: Graphics
Classifier: Topic :: Text Processing :: General
Classifier: License :: OSI Approved :: MIT License
Classifier: Programming Language :: Python :: 3
Classifier: Programming Language :: Python :: 3.7
Classifier: Programming Language :: Python :: 3.8
Classifier: Programming Language :: Python :: 3.9
Classifier: Programming Language :: Python :: 3.10
Classifier: Programming Language :: Python :: 3.11
Requires-Python: >=3.7
License-File: LICENSE.md
Requires-Dist: Pillow>=8.0.0
Requires-Dist: numpy<2.0.0,>=1.19.0
Provides-Extra: advanced-edge-detection
Requires-Dist: scipy>=1.7.0; extra == "advanced-edge-detection"
Requires-Dist: scikit-image<0.22.0,>=0.18.0; extra == "advanced-edge-detection"
Dynamic: author
Dynamic: author-email
Dynamic: classifier
Dynamic: description
Dynamic: description-content-type
Dynamic: home-page
Dynamic: keywords
Dynamic: license
Dynamic: license-file
Dynamic: project-url
Dynamic: provides-extra
Dynamic: requires-dist
Dynamic: requires-python
Dynamic: summary
